tempo_client/__init__.py
tempo_client/client.py
tempo_client/test.py
tempo_client-0.0.1.dist-info/LICENSE.txt
tempo_client-0.0.1.dist-info/METADATA
tempo_client-0.0.1.dist-info/RECORD
tempo_client-0.0.1.dist-info/WHEEL
tempo_client-0.0.1.dist-info/top_level.txt
