Metadata-Version: 2.1
Name: tempo-client
Version: 0.0.1
Summary: A Python client to Tempo Timesheet REST API
Home-page: https://github.com/pwitab/tempo-client
Author: Henrik Palmlund Wahlgren @ Palmlund Wahlgren Innovative Technology AB
Author-email: henrik@pwit.se
License: MIT
Keywords: Tempo,Tempo Timesheets,Timesheets
Platform: UNKNOWN
Requires-Dist: requests
